build.sh
logo.svg
setup.py
tests/__init__.py
tests/continuation_at_start.vcf
tests/dot_at_line_start.vcf
tests/invalid_begin.vcf
tests/invalid_language_value.vcf
tests/invalid_param_name.vcf
tests/invalid_param_value.vcf
tests/invalid_property_foo.vcf
tests/invalid_value_count_wp.vcf
tests/line_ending_mac.vcf
tests/line_ending_unix.vcf
tests/minimal.vcf
tests/mismatch_group.vcf
tests/missing_end.vcf
tests/missing_fn.vcf
tests/missing_group.vcf
tests/missing_n.vcf
tests/missing_n_value.vcf
tests/missing_param_value.vcf
tests/missing_photo_param.vcf
tests/missing_properties.vcf
tests/missing_start.vcf
tests/missing_version.vcf
tests/rfc_2426_a.vcf
tests/rfc_2426_b.vcf
tests/scrambled_case.vcf
tests/tests.py
vCard_module.egg-info/PKG-INFO
vCard_module.egg-info/SOURCES.txt
vCard_module.egg-info/dependency_links.txt
vCard_module.egg-info/entry_points.txt
vCard_module.egg-info/requires.txt
vCard_module.egg-info/top_level.txt
vcard/__init__.py
vcard/vcard.py
vcard/vcard_defs.py
vcard/vcard_utils.py
vcard/vcard_validators.py